[
  {
    "Nombre": "Comité de idiomas virtual o regular",
    "FechaInicio": "27-08-2020",
    "FechaCierre": "27-08-2020",
    "numNotificaciones": 0,
    "Tipo": "GENERAL",
    "Ubicacion": "Calle 12 C N 6-25",
    "Notificaciones": []
  },
  {
    "Nombre": "Grupos Cancelados Programas Escuela de Medicina y Ciencias de la Salud. Año 2019",
    "FechaInicio": "18-12-2020",
    "FechaCierre": "18-12-2020",
    "numNotificaciones": 0,
    "Tipo": "GENERAL",
    "Ubicacion": "Calle 12 C N 6-25",
    "Notificaciones": []
  },
  {
    "Nombre": "Registro de Asignaturas estudiantes antiguos  Programas Claustro,Escuela de Ciencias Humanas, Matemáticas",
    "FechaInicio": "08-01-2020",
    "FechaCierre": "13-01-2020",
    "numNotificaciones": 0,
    "Tipo": "GENERAL",
    "Ubicacion": "Calle 12 C N 6-25",
    "Notificaciones": []
  },
  {
    "Nombre": "Grupos Cancelados Programas Escuela de Administración y Facultad de Creación: Teatro Musical",
    "FechaInicio": "10-01-2020",
    "FechaCierre": "10-01-2020",
    "numNotificaciones": 0,
    "Tipo": "GENERAL",
    "Ubicacion": "Calle 12 C N 6-25",
    "Notificaciones": []
  },
  {
    "Nombre": "Comité de idiomas virtual o regular",
    "FechaInicio": "20-01-2020",
    "FechaCierre": "20-01-2020",
    "numNotificaciones": 0,
    "Tipo": "GENERAL",
    "Ubicacion": "Calle 12 C N 6-25",
    "Notificaciones": []
  },
  {
    "Nombre": "Actividades RoseA - Inmesión en inglés",
    "FechaInicio": "27-01-2020",
    "FechaCierre": "16-05-2020",
    "numNotificaciones": 0,
    "Tipo": "GENERAL",
    "Ubicacion": "Calle 12 C N 6-25",
    "Notificaciones": []
  },
  {
    "Nombre": "Fecha límite para tramitar retiro de cursos para todos los programas",
    "FechaInicio": "15-03-2021",
    "FechaCierre": "15-03-2021",
    "numNotificaciones": 0,
    "Tipo": "GENERAL",
    "Ubicacion": "Calle 12 C N 6-25",
    "Notificaciones": []
  },
  {
    "Nombre": "Semana Santa",
    "FechaInicio": "06-04-2020",
    "FechaCierre": "10-04-2020",
    "numNotificaciones": 0,
    "Tipo": "GENERAL",
    "Ubicacion": "Calle 12 C N 6-25",
    "Notificaciones": []
  },
  {
    "Nombre": "Semana del Bienestar",
    "FechaInicio": "20-04-2020",
    "FechaCierre": "24-04-2020",
    "numNotificaciones": 0,
    "Tipo": "GENERAL",
    "Ubicacion": "Calle 12 C N 6-25",
    "Notificaciones": []
  },
  {
    "Nombre": "Presentación de los estudiantes de sus solicitudes a las Secretarias Académicas para el Comité de idiomas virtual o regular",
    "FechaInicio": "20-04-2020",
    "FechaCierre": "20-04-2020",
    "numNotificaciones": 0,
    "Tipo": "GENERAL",
    "Ubicacion": "Calle 12 C N 6-25",
    "Notificaciones": []
  },
  {
    "Nombre": "Comité de idiomas virtual o regular",
    "FechaInicio": "30-04-2020",
    "FechaCierre": "30-04-2020",
    "numNotificaciones": 0,
    "Tipo": "GENERAL",
    "Ubicacion": "Calle 12 C N 6-25",
    "Notificaciones": []
  },
  {
    "Nombre": "Publicación de catálogo web de la oferta académica",
    "FechaInicio": "15-05-2020",
    "FechaCierre": "15-05-2020",
    "numNotificaciones": 0,
    "Tipo": "GENERAL",
    "Ubicacion": "Calle 12 C N 6-25",
    "Notificaciones": []
  },
  {
    "Nombre": "Día del profesor",
    "FechaInicio": "15-05-2020",
    "FechaCierre": "15-05-2020",
    "numNotificaciones": 0,
    "Tipo": "GENERAL",
    "Ubicacion": "Calle 12 C N 6-25",
    "Notificaciones": []
  },
  {
    "Nombre": "Comité de idiomas institucional presidido por la Sra. Vicerrectora - CAI institucional",
    "FechaInicio": "20-05-2020",
    "FechaCierre": "20-05-2020",
    "numNotificaciones": 0,
    "Tipo": "GENERAL",
    "Ubicacion": "Calle 12 C N 6-25",
    "Notificaciones": []
  },
  {
    "Nombre": "Registro de asignaturas todos los programas",
    "FechaInicio": "29-05-2020",
    "FechaCierre": "31-05-2020",
    "numNotificaciones": 0,
    "Tipo": "GENERAL",
    "Ubicacion": "Calle 12 C N 6-25",
    "Notificaciones": []
  },
  {
    "Nombre": "Registro intersemestrales",
    "FechaInicio": "29-05-2020",
    "FechaCierre": "31-05-2020",
    "numNotificaciones": 0,
    "Tipo": "GENERAL",
    "Ubicacion": "Calle 12 C N 6-25",
    "Notificaciones": []
  },
  {
    "Nombre": "Presentación de los estudiantes de sus solicitudes a las Secretarias Académicas para el Comité de idiomas virtual o regular",
    "FechaInicio": "01-06-2020",
    "FechaCierre": "01-06-2020",
    "numNotificaciones": 0,
    "Tipo": "GENERAL",
    "Ubicacion": "Calle 12 C N 6-25",
    "Notificaciones": []
  },
  {
    "Nombre": "Grupos Cancelados intersemestrales",
    "FechaInicio": "01-06-2020",
    "FechaCierre": "01-06-2020",
    "numNotificaciones": 0,
    "Tipo": "GENERAL",
    "Ubicacion": "Calle 12 C N 6-25",
    "Notificaciones": []
  },
  {
    "Nombre": "Internado Rotatorio",
    "FechaInicio": "01-06-2020",
    "FechaCierre": "30-11-2020",
    "numNotificaciones": 0,
    "Tipo": "GENERAL",
    "Ubicacion": "Calle 12 C N 6-25",
    "Notificaciones": []
  },
  {
    "Nombre": "Publicación de Salones",
    "FechaInicio": "01-06-2020",
    "FechaCierre": "01-06-2020",
    "numNotificaciones": 0,
    "Tipo": "GENERAL",
    "Ubicacion": "Calle 12 C N 6-25",
    "Notificaciones": []
  },
  {
    "Nombre": "Inicio y finalización de clases todos los programas",
    "FechaInicio": "02-06-2020",
    "FechaCierre": "17-07-2020",
    "numNotificaciones": 0,
    "Tipo": "GENERAL",
    "Ubicacion": "Calle 12 C N 6-25",
    "Notificaciones": []
  },
  {
    "Nombre": "Fecha límite para reportar notas tercer corte Medicina e ingresar notas al SIAR",
    "FechaInicio": "07-06-2020",
    "FechaCierre": "07-06-2020",
    "numNotificaciones": 0,
    "Tipo": "GENERAL",
    "Ubicacion": "Calle 12 C N 6-25",
    "Notificaciones": []
  },
  {
    "Nombre": "Comité de idiomas virtual o regular",
    "FechaInicio": "08-06-2020",
    "FechaCierre": "08-06-2020",
    "numNotificaciones": 0,
    "Tipo": "GENERAL",
    "Ubicacion": "Calle 12 C N 6-25",
    "Notificaciones": []
  },
  {
    "Nombre": "Pago cursos intersemestrales",
    "FechaInicio": "10-06-2020",
    "FechaCierre": "10-06-2020",
    "numNotificaciones": 0,
    "Tipo": "GENERAL",
    "Ubicacion": "Calle 12 C N 6-25",
    "Notificaciones": []
  },
  {
    "Nombre": "Publicación de catálogo web de la oferta académica",
    "FechaInicio": "10-06-2020",
    "FechaCierre": "10-06-2020",
    "numNotificaciones": 0,
    "Tipo": "GENERAL",
    "Ubicacion": "Calle 12 C N 6-25",
    "Notificaciones": []
  },
  {
    "Nombre": "Grupos Cancelados Programas Escuela de Medicina y Ciencias de la Salud",
    "FechaInicio": "23-06-2020",
    "FechaCierre": "23-06-2020",
    "numNotificaciones": 0,
    "Tipo": "GENERAL",
    "Ubicacion": "Calle 12 C N 6-25",
    "Notificaciones": []
  },
  {
    "Nombre": "Grupos Cancelados Programas Escuela de Administración y Facultad de Creación: Teatro Musical",
    "FechaInicio": "06-07-2020",
    "FechaCierre": "06-07-2020",
    "numNotificaciones": 0,
    "Tipo": "GENERAL",
    "Ubicacion": "Calle 12 C N 6-25",
    "Notificaciones": []
  },
  {
    "Nombre": "Registro de asignaturas Estudiantes Medicina 1-6",
    "FechaInicio": "15-07-2020",
    "FechaCierre": "15-07-2020",
    "numNotificaciones": 0,
    "Tipo": "GENERAL",
    "Ubicacion": "Calle 12 C N 6-25",
    "Notificaciones": []
  },
  {
    "Nombre": "Cierre académico y normativa académica - Todos los Programas",
    "FechaInicio": "17-07-2020",
    "FechaCierre": "17-07-2020",
    "numNotificaciones": 0,
    "Tipo": "GENERAL",
    "Ubicacion": "Calle 12 C N 6-25",
    "Notificaciones": []
  },
  {
    "Nombre": "Inicio y finalización de actividades programas virtuales DMD - Tercer ciclo",
    "FechaInicio": "20-07-2020",
    "FechaCierre": "26-09-2020",
    "numNotificaciones": 0,
    "Tipo": "GENERAL",
    "Ubicacion": "Calle 12 C N 6-25",
    "Notificaciones": []
  },
  {
    "Nombre": "Segunda fecha. Período pago de matrícula Estudiantes Medicina 1-6",
    "FechaInicio": "23-07-2020",
    "FechaCierre": "23-07-2020",
    "numNotificaciones": 0,
    "Tipo": "GENERAL",
    "Ubicacion": "Calle 12 C N 6-25",
    "Notificaciones": []
  },
  {
    "Nombre": "Retiro de asignaturas de estudiantes Medicina 1-6",
    "FechaInicio": "27-07-2020",
    "FechaCierre": "28-11-2020",
    "numNotificaciones": 0,
    "Tipo": "GENERAL",
    "Ubicacion": "Calle 12 C N 6-25",
    "Notificaciones": []
  },
  {
    "Nombre": "Inicio y finalización de Clases estudiantes Medicina 1-6",
    "FechaInicio": "27-07-2020",
    "FechaCierre": "21-11-2020",
    "numNotificaciones": 0,
    "Tipo": "GENERAL",
    "Ubicacion": "Calle 12 C N 6-25",
    "Notificaciones": []
  },
  {
    "Nombre": "Grupos Cancelados todos los programas",
    "FechaInicio": "28-07-2020",
    "FechaCierre": "28-07-2020",
    "numNotificaciones": 0,
    "Tipo": "GENERAL",
    "Ubicacion": "Calle 12 C N 6-25",
    "Notificaciones": []
  },
  {
    "Nombre": "Publicación de Salones",
    "FechaInicio": "01-08-2020",
    "FechaCierre": "01-08-2020",
    "numNotificaciones": 0,
    "Tipo": "GENERAL",
    "Ubicacion": "Calle 12 C N 6-25",
    "Notificaciones": []
  },
  {
    "Nombre": "Consulta médica inicial",
    "FechaInicio": "03-08-2020",
    "FechaCierre": "30-09-2020",
    "numNotificaciones": 0,
    "Tipo": "GENERAL",
    "Ubicacion": "Calle 12 C N 6-25",
    "Notificaciones": []
  },
  {
    "Nombre": "Inicio y finalización de clases todos los programas",
    "FechaInicio": "03-08-2020",
    "FechaCierre": "28-11-2020",
    "numNotificaciones": 0,
    "Tipo": "GENERAL",
    "Ubicacion": "Calle 12 C N 6-25",
    "Notificaciones": []
  },
  {
    "Nombre": "Retiro de asignaturas todos los programas",
    "FechaInicio": "03-08-2020",
    "FechaCierre": "28-11-2020",
    "numNotificaciones": 0,
    "Tipo": "GENERAL",
    "Ubicacion": "Calle 12 C N 6-25",
    "Notificaciones": []
  },
  {
    "Nombre": "Registro de asignaturas Estudiantes Medicina 7-8",
    "FechaInicio": "06-08-2020",
    "FechaCierre": "06-08-2020",
    "numNotificaciones": 0,
    "Tipo": "GENERAL",
    "Ubicacion": "Calle 12 C N 6-25",
    "Notificaciones": []
  },
  {
    "Nombre": "Registro de asignaturas Estudiantes Medicina 9-10",
    "FechaInicio": "06-08-2020",
    "FechaCierre": "06-08-2020",
    "numNotificaciones": 0,
    "Tipo": "GENERAL",
    "Ubicacion": "Calle 12 C N 6-25",
    "Notificaciones": []
  },
  {
    "Nombre": "Período para solicitud de homologaciones y reconocimientos de otros períodos",
    "FechaInicio": "10-08-2020",
    "FechaCierre": "30-11-2020",
    "numNotificaciones": 0,
    "Tipo": "GENERAL",
    "Ubicacion": "Calle 12 C N 6-25",
    "Notificaciones": []
  },
  {
    "Nombre": "Período para solicitud de exámenes de validación",
    "FechaInicio": "11-08-2020",
    "FechaCierre": "28-11-2020",
    "numNotificaciones": 0,
    "Tipo": "GENERAL",
    "Ubicacion": "Calle 12 C N 6-25",
    "Notificaciones": []
  },
  {
    "Nombre": "Fecha límite de reserva de cupo estudiantes antiguos y retiro de asignaturas con beneficio económico Todos los Programas",
    "FechaInicio": "11-08-2020",
    "FechaCierre": "11-08-2020",
    "numNotificaciones": 0,
    "Tipo": "GENERAL",
    "Ubicacion": "Calle 12 C N 6-25",
    "Notificaciones": []
  },
  {
    "Nombre": "Fecha límite de reserva de cupo estudiantes antiguos y retiro de asignaturas con beneficio económico estudiantes Medicina 1-6",
    "FechaInicio": "11-08-2020",
    "FechaCierre": "11-08-2020",
    "numNotificaciones": 0,
    "Tipo": "GENERAL",
    "Ubicacion": "Calle 12 C N 6-25",
    "Notificaciones": []
  },
  {
    "Nombre": "Presentación de los estudiantes de sus solicitudes a las Secretarias Académicas para el Comité de idiomas virtual o regular",
    "FechaInicio": "18-08-2020",
    "FechaCierre": "18-08-2020",
    "numNotificaciones": 0,
    "Tipo": "GENERAL",
    "Ubicacion": "Calle 12 C N 6-25",
    "Notificaciones": []
  },
  {
    "Nombre": "Fecha máxima reportar primer corte Estudiantes Medicina 1-6",
    "FechaInicio": "24-08-2020",
    "FechaCierre": "30-08-2020",
    "numNotificaciones": 0,
    "Tipo": "GENERAL",
    "Ubicacion": "Calle 12 C N 6-25",
    "Notificaciones": []
  },
  {
    "Nombre": "Inicio y finalización de Clases  estudiantes Medicina 9-10",
    "FechaInicio": "01-09-2020",
    "FechaCierre": "19-12-2020",
    "numNotificaciones": 0,
    "Tipo": "GENERAL",
    "Ubicacion": "Calle 12 C N 6-25",
    "Notificaciones": []
  },
  {
    "Nombre": "Retiro de asignaturas de estudiantes Medicina 9-10",
    "FechaInicio": "01-09-2020",
    "FechaCierre": "12-12-2020",
    "numNotificaciones": 0,
    "Tipo": "GENERAL",
    "Ubicacion": "Calle 12 C N 6-25",
    "Notificaciones": []
  },
  {
    "Nombre": "Inicio y finalización de Clases estudiantes Medicina 7-8",
    "FechaInicio": "01-09-2020",
    "FechaCierre": "06feb.",
    "numNotificaciones": 0,
    "Tipo": "GENERAL",
    "Ubicacion": "Calle 12 C N 6-25",
    "Notificaciones": []
  },
  {
    "Nombre": "Inicio y finalización de Clases estudiantes Medicina 9-10 con módulos electivos de profundización en investigación",
    "FechaInicio": "01-09-2020",
    "FechaCierre": "14-11-2020",
    "numNotificaciones": 0,
    "Tipo": "GENERAL",
    "Ubicacion": "Calle 12 C N 6-25",
    "Notificaciones": []
  },
  {
    "Nombre": "Retiro de asignaturas de estudiantes Medicina 9-10 con módulos electivos de profundización en investigación",
    "FechaInicio": "01-09-2020",
    "FechaCierre": "07-11-2020",
    "numNotificaciones": 0,
    "Tipo": "GENERAL",
    "Ubicacion": "Calle 12 C N 6-25",
    "Notificaciones": []
  },
  {
    "Nombre": "Retiro de asignaturas de estudiantes Medicina 7-8",
    "FechaInicio": "01-09-2020",
    "FechaCierre": "30-01-2020",
    "numNotificaciones": 0,
    "Tipo": "GENERAL",
    "Ubicacion": "Calle 12 C N 6-25",
    "Notificaciones": []
  },
  {
    "Nombre": "Fecha máxima reportar primer corte todos los programas",
    "FechaInicio": "07-09-2020",
    "FechaCierre": "13-09-2020",
    "numNotificaciones": 0,
    "Tipo": "GENERAL",
    "Ubicacion": "Calle 12 C N 6-25",
    "Notificaciones": []
  },
  {
    "Nombre": "Fecha límite de reserva de cupo estudiantes antiguos y retiro de asignaturas con beneficio económico estudiantes Medicina 7-8",
    "FechaInicio": "11-09-2020",
    "FechaCierre": "11-09-2020",
    "numNotificaciones": 0,
    "Tipo": "GENERAL",
    "Ubicacion": "Calle 12 C N 6-25",
    "Notificaciones": []
  },
  {
    "Nombre": "Fecha límite de reserva de cupo estudiantes antiguos y retiro de asignaturas con beneficio económico estudiantes Medicina 9-10",
    "FechaInicio": "11-09-2020",
    "FechaCierre": "11-09-2020",
    "numNotificaciones": 0,
    "Tipo": "GENERAL",
    "Ubicacion": "Calle 12 C N 6-25",
    "Notificaciones": []
  },
  {
    "Nombre": "Semana de Receso",
    "FechaInicio": "21-09-2020",
    "FechaCierre": "26-09-2020",
    "numNotificaciones": 0,
    "Tipo": "GENERAL",
    "Ubicacion": "Calle 12 C N 6-25",
    "Notificaciones": []
  },
  {
    "Nombre": "Comité de idiomas institucional presidido por la Sra. Vicerrectora - CAI institucional",
    "FechaInicio": "24-09-2020",
    "FechaCierre": "24-09-2020",
    "numNotificaciones": 0,
    "Tipo": "GENERAL",
    "Ubicacion": "Calle 12 C N 6-25",
    "Notificaciones": []
  },
  {
    "Nombre": "Comité de idiomas institucional presedido por el Vicerrector",
    "FechaInicio": "24-09-2020",
    "FechaCierre": "24-09-2020",
    "numNotificaciones": 0,
    "Tipo": "GENERAL",
    "Ubicacion": "Calle 12 C N 6-25",
    "Notificaciones": []
  },
  {
    "Nombre": "Semana del Bienestar",
    "FechaInicio": "02-10-2020",
    "FechaCierre": "16-10-2020",
    "numNotificaciones": 0,
    "Tipo": "GENERAL",
    "Ubicacion": "Calle 12 C N 6-25",
    "Notificaciones": []
  },
  {
    "Nombre": "Fecha máxima reportar segundo corte Estudiantes Medicina 1-6",
    "FechaInicio": "04-10-2020",
    "FechaCierre": "10-10-2020",
    "numNotificaciones": 0,
    "Tipo": "GENERAL",
    "Ubicacion": "Calle 12 C N 6-25",
    "Notificaciones": []
  },
  {
    "Nombre": "Inicio y finalización de actividades programas virtuales DMD - Cuarto ciclo",
    "FechaInicio": "05-10-2020",
    "FechaCierre": "12-12-2020",
    "numNotificaciones": 0,
    "Tipo": "GENERAL",
    "Ubicacion": "Calle 12 C N 6-25",
    "Notificaciones": []
  },
  {
    "Nombre": "Fecha máxima reportar segundo corte todos los programas",
    "FechaInicio": "01-11-2020",
    "FechaCierre": "07-11-2020",
    "numNotificaciones": 0,
    "Tipo": "GENERAL",
    "Ubicacion": "Calle 12 C N 6-25",
    "Notificaciones": []
  },
  {
    "Nombre": "Presentación de los estudiantes de sus solicitudes a las Secretarias Académicas para el Comité de idiomas virtual o regular",
    "FechaInicio": "09-11-2020",
    "FechaCierre": "09-11-2020",
    "numNotificaciones": 0,
    "Tipo": "GENERAL",
    "Ubicacion": "Calle 12 C N 6-25",
    "Notificaciones": []
  },
  {
    "Nombre": "Período de Evaluaciones Finales Pregrado Medicina 9-10 con módulos electivos de profundización en investigación",
    "FechaInicio": "09-11-2020",
    "FechaCierre": "14-11-2020",
    "numNotificaciones": 0,
    "Tipo": "GENERAL",
    "Ubicacion": "Calle 12 C N 6-25",
    "Notificaciones": []
  },
  {
    "Nombre": "Envío de los soportes documentales y formatos de presentación a la Secretaría Técnica del CAI – Dirección de Estudiantes  por parte de los Secretarios Académicos",
    "FechaInicio": "13-11-2020",
    "FechaCierre": "13-11-2020",
    "numNotificaciones": 0,
    "Tipo": "GENERAL",
    "Ubicacion": "Calle 12 C N 6-25",
    "Notificaciones": []
  },
  {
    "Nombre": "Comité de Idiomas - Casos estudiantiles",
    "FechaInicio": "20-11-2020",
    "FechaCierre": "20-11-2020",
    "numNotificaciones": 0,
    "Tipo": "GENERAL",
    "Ubicacion": "Calle 12 C N 6-25",
    "Notificaciones": []
  },
  {
    "Nombre": "Comité de idiomas virtual o regular",
    "FechaInicio": "20-11-2020",
    "FechaCierre": "20-11-2020",
    "numNotificaciones": 0,
    "Tipo": "GENERAL",
    "Ubicacion": "Calle 12 C N 6-25",
    "Notificaciones": []
  },
  {
    "Nombre": "Período de Evaluaciones Finales todos los programas de Estudios Universitarios y Fortalecimiento Académico",
    "FechaInicio": "23-11-2020",
    "FechaCierre": "28-11-2020",
    "numNotificaciones": 0,
    "Tipo": "GENERAL",
    "Ubicacion": "Calle 12 C N 6-25",
    "Notificaciones": []
  },
  {
    "Nombre": "Fecha límite de reserva de cupo estudiantes antiguos y retiro de asignaturas con beneficio académico estudiantes Medicina 1-6",
    "FechaInicio": "28-11-2020",
    "FechaCierre": "28-11-2020",
    "numNotificaciones": 0,
    "Tipo": "GENERAL",
    "Ubicacion": "Calle 12 C N 6-25",
    "Notificaciones": []
  },
  {
    "Nombre": "Último día del Período Académico (incluye evaluaciones finales)  todos los programas de Estudios Universitarios y Fortalecimiento Académico",
    "FechaInicio": "28-11-2020",
    "FechaCierre": "28-11-2020",
    "numNotificaciones": 0,
    "Tipo": "GENERAL",
    "Ubicacion": "Calle 12 C N 6-25",
    "Notificaciones": []
  },
  {
    "Nombre": "Fecha límite de reserva de cupo estudiantes antiguos y retiro de asignaturas con beneficio académico Todos los Programas",
    "FechaInicio": "28-11-2020",
    "FechaCierre": "28-11-2020",
    "numNotificaciones": 0,
    "Tipo": "GENERAL",
    "Ubicacion": "Calle 12 C N 6-25",
    "Notificaciones": []
  },
  {
    "Nombre": "Período de Evaluaciones Finales Estudiantes Medicina 1-6",
    "FechaInicio": "30-11-2020",
    "FechaCierre": "05-12-2020",
    "numNotificaciones": 0,
    "Tipo": "GENERAL",
    "Ubicacion": "Calle 12 C N 6-25",
    "Notificaciones": []
  },
  {
    "Nombre": "Fecha máxima reportar tercer corte Estudiantes Medicina 1-6",
    "FechaInicio": "30-11-2020",
    "FechaCierre": "07-12-2020",
    "numNotificaciones": 0,
    "Tipo": "GENERAL",
    "Ubicacion": "Calle 12 C N 6-25",
    "Notificaciones": []
  },
  {
    "Nombre": "Período de Evaluaciones Finales Todos los Programas",
    "FechaInicio": "30-11-2020",
    "FechaCierre": "05-12-2020",
    "numNotificaciones": 0,
    "Tipo": "GENERAL",
    "Ubicacion": "Calle 12 C N 6-25",
    "Notificaciones": []
  },
  {
    "Nombre": "Cierre académico y normativa registro y control académico  programas de Estudios Universitarios y Fortalecimiento Académico",
    "FechaInicio": "02-12-2020",
    "FechaCierre": "02-12-2020",
    "numNotificaciones": 0,
    "Tipo": "GENERAL",
    "Ubicacion": "Calle 12 C N 6-25",
    "Notificaciones": []
  },
  {
    "Nombre": "Período para solicitud de homologaciones y reconocimientos del período que culmina",
    "FechaInicio": "03-12-2020",
    "FechaCierre": "18-12-2020",
    "numNotificaciones": 0,
    "Tipo": "GENERAL",
    "Ubicacion": "Calle 12 C N 6-25",
    "Notificaciones": []
  },
  {
    "Nombre": "Último día del Período Académico (incluye Evaluaciones finales) Estudiantes Medicina 1-6",
    "FechaInicio": "05-12-2020",
    "FechaCierre": "05-12-2020",
    "numNotificaciones": 0,
    "Tipo": "GENERAL",
    "Ubicacion": "Calle 12 C N 6-25",
    "Notificaciones": []
  },
  {
    "Nombre": "Último día del Período Académico (Incluye evaluaciones finales) Todos los Programas",
    "FechaInicio": "05-12-2020",
    "FechaCierre": "05-12-2020",
    "numNotificaciones": 0,
    "Tipo": "GENERAL",
    "Ubicacion": "Calle 12 C N 6-25",
    "Notificaciones": []
  },
  {
    "Nombre": "Fecha máxima reportar tercer corte todos los programas",
    "FechaInicio": "08-12-2020",
    "FechaCierre": "08-12-2020",
    "numNotificaciones": 0,
    "Tipo": "GENERAL",
    "Ubicacion": "Calle 12 C N 6-25",
    "Notificaciones": []
  },
  {
    "Nombre": "Cierre de actas Secretarias Académicas - Todos los Programas",
    "FechaInicio": "08-12-2020",
    "FechaCierre": "08-12-2020",
    "numNotificaciones": 0,
    "Tipo": "GENERAL",
    "Ubicacion": "Calle 12 C N 6-25",
    "Notificaciones": []
  },
  {
    "Nombre": "Cierre académico y normativa académica - Todos los Programas",
    "FechaInicio": "09-12-2020",
    "FechaCierre": "09-12-2020",
    "numNotificaciones": 0,
    "Tipo": "GENERAL",
    "Ubicacion": "Calle 12 C N 6-25",
    "Notificaciones": []
  },
  {
    "Nombre": "Publicación Web de Notas Definitivas",
    "FechaInicio": "12-12-2020",
    "FechaCierre": "12-12-2020",
    "numNotificaciones": 0,
    "Tipo": "GENERAL",
    "Ubicacion": "",
    "Notificaciones": []
  },
  {
    "Nombre": "Fecha límite de reserva de cupo estudiantes antiguos y retiro de asignaturas con beneficio académico estudiantes Medicina 9-10",
    "FechaInicio": "12-12-2020",
    "FechaCierre": "12-12-2020",
    "numNotificaciones": 0,
    "Tipo": "GENERAL",
    "Ubicacion": "Calle 12 C N 6-25",
    "Notificaciones": []
  },
  {
    "Nombre": "Período de Evaluaciones Finales Pregrado Medicina 9-10",
    "FechaInicio": "14-12-2020",
    "FechaCierre": "19-12-2020",
    "numNotificaciones": 0,
    "Tipo": "GENERAL",
    "Ubicacion": "Calle 12 C N 6-25",
    "Notificaciones": []
  },
  {
    "Nombre": "Cierre de actas Secretaria Académica - Pregrado Medicina",
    "FechaInicio": "15-12-2020",
    "FechaCierre": "15-12-2020",
    "numNotificaciones": 0,
    "Tipo": "GENERAL",
    "Ubicacion": "",
    "Notificaciones": []
  },
  {
    "Nombre": "Último día del Período Académico (incluye Evaluaciones finales) Pregrado Medicina 9-10",
    "FechaInicio": "19-12-2020",
    "FechaCierre": "19-12-2020",
    "numNotificaciones": 0,
    "Tipo": "GENERAL",
    "Ubicacion": "Calle 12 C N 6-25",
    "Notificaciones": []
  },
  {
    "Nombre": "Cierre académico Estudiantes Medicina 9-10",
    "FechaInicio": "22-12-2020",
    "FechaCierre": "22-12-2020",
    "numNotificaciones": 0,
    "Tipo": "GENERAL",
    "Ubicacion": "Calle 12 C N 6-25",
    "Notificaciones": []
  },
  {
    "Nombre": "Fecha máxima reportar notas definitivas Estudiantes Medicina 9-10",
    "FechaInicio": "22-12-2020",
    "FechaCierre": "19-01-2020",
    "numNotificaciones": 0,
    "Tipo": "GENERAL",
    "Ubicacion": "",
    "Notificaciones": []
  },
  {
    "Nombre": "Fecha límite de reserva de cupo estudiantes antiguos y retiro de asignaturas con beneficio académico estudiantes Medicina 7-8",
    "FechaInicio": "30-01-2020",
    "FechaCierre": "30-01-2020",
    "numNotificaciones": 0,
    "Tipo": "GENERAL",
    "Ubicacion": "Calle 12 C N 6-25",
    "Notificaciones": []
  },
  {
    "Nombre": "Período de Evaluaciones Finales Pregrado Medicina 7-8",
    "FechaInicio": "01feb.",
    "FechaCierre": "06feb.",
    "numNotificaciones": 0,
    "Tipo": "GENERAL",
    "Ubicacion": "Calle 12 C N 6-25",
    "Notificaciones": []
  },
  {
    "Nombre": "Fecha máxima reportar notas definitivas Estudiantes Medicina 7-8",
    "FechaInicio": "06feb.",
    "FechaCierre": "19feb.",
    "numNotificaciones": 0,
    "Tipo": "GENERAL",
    "Ubicacion": "Calle 12 C N 6-25",
    "Notificaciones": []
  },
  {
    "Nombre": "Último día del Período Académico (incluye Evaluaciones finales) Pregrado Medicina 7-8",
    "FechaInicio": "06feb.",
    "FechaCierre": "06feb.",
    "numNotificaciones": 0,
    "Tipo": "GENERAL",
    "Ubicacion": "Calle 12 C N 6-25",
    "Notificaciones": []
  },
  {
    "Nombre": "Cierre académico Estudiantes Medicina 7-8",
    "FechaInicio": "19feb.",
    "FechaCierre": "19feb.",
    "numNotificaciones": 0,
    "Tipo": "GENERAL",
    "Ubicacion": "Calle 12 C N 6-25",
    "Notificaciones": []
  }
]